hikkalls/__init__.py
hikkalls/__version__.py
hikkalls/binding.py
hikkalls/environment.py
hikkalls/exceptions.py
hikkalls/ffprobe.py
hikkalls/file_manager.py
hikkalls/hikkalls.py
hikkalls/hikkalls_session.py
hikkalls/scaffold.py
hikkalls/stream_type.py
hikkalls/sync.py
hikkalls/version_manager.py
hikkalls/custom_api/__init__.py
hikkalls/custom_api/custom_api.py
hikkalls/dist/binding.js
hikkalls/dist/buffer_optimized.js
hikkalls/dist/ffmpeg_reader.js
hikkalls/dist/file_reader.js
hikkalls/dist/index.js
hikkalls/dist/rtc-connection.js
hikkalls/dist/sdp-builder.js
hikkalls/dist/stream.js
hikkalls/dist/tgcalls.js
hikkalls/dist/types.js
hikkalls/dist/utils.js
hikkalls/handlers/__init__.py
hikkalls/handlers/handlers_holder.py
hikkalls/media_devices/__init__.py
hikkalls/media_devices/device_info.py
hikkalls/media_devices/media_devices.py
hikkalls/media_devices/screen_info.py
hikkalls/methods/__init__.py
hikkalls/methods/core/__init__.py
hikkalls/methods/core/binding_runner.py
hikkalls/methods/core/join_voice_call.py
hikkalls/methods/core/leave_voice_call.py
hikkalls/methods/core/set_video_call_status.py
hikkalls/methods/decorators/__init__.py
hikkalls/methods/decorators/on_closed_voice_chat.py
hikkalls/methods/decorators/on_group_call_invite.py
hikkalls/methods/decorators/on_kicked.py
hikkalls/methods/decorators/on_left.py
hikkalls/methods/decorators/on_participants_change.py
hikkalls/methods/decorators/on_raw_update.py
hikkalls/methods/decorators/on_stream_end.py
hikkalls/methods/groups/__init__.py
hikkalls/methods/groups/active_calls.py
hikkalls/methods/groups/calls.py
hikkalls/methods/groups/change_volume_call.py
hikkalls/methods/groups/get_active_call.py
hikkalls/methods/groups/get_call.py
hikkalls/methods/groups/get_participants.py
hikkalls/methods/groups/join_group_call.py
hikkalls/methods/groups/leave_group_call.py
hikkalls/methods/handlers/__init__.py
hikkalls/methods/handlers/raw_update_handler.py
hikkalls/methods/handlers/stream_ended_handler.py
hikkalls-0.1.10.dist-info/LICENSE
hikkalls-0.1.10.dist-info/METADATA
hikkalls-0.1.10.dist-info/WHEEL
hikkalls-0.1.10.dist-info/top_level.txt
hikkalls-0.1.10.dist-info/RECORD
